{
    "version": "1.0.0",
    "files": [
        {
            "name": "universal-ssh-keys.cfg",
            "url": "https://raw.githubusercontent.com/FootGod-bot/Universal-ssh-keys/refs/heads/main/universal-ssh-keys.cfg",
            "path": "/etc/pve/universal-ssh-keys.cfg"
        },
        {
            "name": "apply-universal-keys.sh",
            "url": "https://raw.githubusercontent.com/FootGod-bot/Universal-ssh-keys/refs/heads/main/apply-universal-keys.sh",
            "path": "/usr/local/bin/apply-universal-keys.sh"
        }
    ],
    "permissions": [
        {
            "path": "/opt/mysystem/main.py",
            "chmod": "755"
        },
        {
            "path": "/opt/mysystem/config.json",
            "chmod": "644"
        }
    ],
    "python_requirements": [
        "requests",
        "flask"
    ],
    "apt_requirements": [
        "curl",
        "wget",
        "vim",
        "git",
        "python3-pip"
    ],
    "changelog": "https://raw.githubusercontent.com/<your-repo>/CHANGELOG.md"
}
